{
    "pagination": {
        "last_visible_page": 3,
        "has_next_page": true
    },
    "data": [
        {
            "mal_id": 1,
            "url": "https:\/\/myanimelist.net\/anime\/20\/Naruto\/episode\/1",
            "title": "Enter: Naruto Uzumaki!",
            "title_japanese": "\u53c2\u4e0a! \u3046\u305a\u307e\u304d\u30ca\u30eb\u30c8",
            "title_romanji": "Sanjou! Uzumaki Naruto\u00a0",
            "aired": "2002-10-03T00:00:00+00:00",
            "score": 4.2,
            "filler": false,
            "recap": false,
            "forum_url": "https:\/\/myanimelist.net\/forum\/?topicid=99623"
        },
        {
            "mal_id": 2,
            "url": "https:\/\/myanimelist.net\/anime\/20\/Naruto\/episode\/2",
            "title": "My Name is Konohamaru!",
            "title_japanese": "\u6728\u30ce\u8449\u4e38\u3060 \u30b3\u30ec!",
            "title_romanji": "Konohamaru da Kore!\u00a0",
            "aired": "2002-10-10T00:00:00+00:00",
            "score": 4,
            "filler": false,
            "recap": false,
            "forum_url": "https:\/\/myanimelist.net\/forum\/?topicid=99805"
        },
        {
            "mal_id": 3,
            "url": "https:\/\/myanimelist.net\/anime\/20\/Naruto\/episode\/3",
            "title": "Sasuke and Sakura: Friends or Foes?",
            "title_japanese": "\u5bbf\u6575!?\u30b5\u30b9\u30b1\u3068\u30b5\u30af\u30e9",
            "title_romanji": "Shukuteki!? Sasuke to Sakura\u00a0",
            "aired": "2002-10-17T00:00:00+00:00",
            "score": 4.1,
            "filler": false,
            "recap": false,
            "forum_url": "https:\/\/myanimelist.net\/forum\/?topicid=99919"
        },
        {
            "mal_id": 4,
            "url": "https:\/\/myanimelist.net\/anime\/20\/Naruto\/episode\/4",
            "title": "Pass or Fail: Survival Test",
            "title_japanese": "\u8a66\u7df4!\u30b5\u30d0\u30a4\u30d0\u30eb\u6f14\u7fd2",
            "title_romanji": "Shiren! Survival Enshuu\u00a0",
            "aired": "2002-10-24T00:00:00+00:00",
            "score": 4.3,
            "filler": false,
            "recap": false,
            "forum_url": "https:\/\/myanimelist.net\/forum\/?topicid=99929"
        },
        {
            "mal_id": 5,
            "url": "https:\/\/myanimelist.net\/anime\/20\/Naruto\/episode\/5",
            "title": "You Failed! Kakashi's Final Decision",
            "title_japanese": "\u5931\u683c?\u30ab\u30ab\u30b7\u306e\u7d50\u8ad6",
            "title_romanji": "Shikkaku? Kakashi no Ketsuron\u00a0",
            "aired": "2002-10-31T00:00:00+00:00",
            "score": 4.3,
            "filler": false,
            "recap": false,
            "forum_url": "https:\/\/myanimelist.net\/forum\/?topicid=99634"
        },
        {
            "mal_id": 6,
            "url": "https:\/\/myanimelist.net\/anime\/20\/Naruto\/episode\/6",
            "title": "A Dangerous Mission! Journey to the Land of Waves!",
            "title_japanese": "\u91cd\u8981\u4efb\u52d9!\u6ce2\u306e\u56fd\u3078\u8d85\u51fa\u767a!",
            "title_romanji": "Juuyou Ninmu! Nami no Kuni e Chou-shuppatsu!\u00a0",
            "aired": "2002-11-07T00:00:00+00:00",
            "score": 4.2,
            "filler": false,
            "recap": false,
            "forum_url": "https:\/\/myanimelist.net\/forum\/?topicid=99932"
        },
        {
            "mal_id": 7,
            "url": "https:\/\/myanimelist.net\/anime\/20\/Naruto\/episode\/7",
            "title": "The Assassin of the Mist!",
            "title_japanese": "\u9727\u306e\u6697\u6bba\u8005!",
            "title_romanji": "Kiri no Ansatsusha!\u00a0",
            "aired": "2002-11-14T00:00:00+00:00",
            "score": 4.2,
            "filler": false,
            "recap": false,
            "forum_url": "https:\/\/myanimelist.net\/forum\/?topicid=99937"
        },
        {
            "mal_id": 8,
            "url": "https:\/\/myanimelist.net\/anime\/20\/Naruto\/episode\/8",
            "title": "The Oath of Pain",
            "title_japanese": "\u75db\u307f\u306b\u8a93\u3046\u6c7a\u610f",
            "title_romanji": "Itami ni Chikau Ketsui\u00a0",
            "aired": "2002-11-21T00:00:00+00:00",
            "score": 4.3,
            "filler": false,
            "recap": false,
            "forum_url": "https:\/\/myanimelist.net\/forum\/?topicid=100035"
        },
        {
            "mal_id": 9,
            "url": "https:\/\/myanimelist.net\/anime\/20\/Naruto\/episode\/9",
            "title": "Kakashi: Sharingan Warrior",
            "title_japanese": "\u5199\u8f2a\u773c\u306e\u30ab\u30ab\u30b7",
            "title_romanji": "Sharingan no Kakashi\u00a0",
            "aired": "2002-11-28T00:00:00+00:00",
            "score": 4.3,
            "filler": false,
            "recap": false,
            "forum_url": "https:\/\/myanimelist.net\/forum\/?topicid=87148"
        },
        {
            "mal_id": 10,
            "url": "https:\/\/myanimelist.net\/anime\/20\/Naruto\/episode\/10",
            "title": "The Forest of Chakra",
            "title_japanese": "\u30c1\u30e3\u30af\u30e9\u306e\u68ee",
            "title_romanji": "Chakra no Mori\u00a0",
            "aired": "2002-12-05T00:00:00+00:00",
            "score": 4,
            "filler": false,
            "recap": false,
            "forum_url": "https:\/\/myanimelist.net\/forum\/?topicid=101533"
        },
        {
            "mal_id": 11,
            "url": "https:\/\/myanimelist.net\/anime\/20\/Naruto\/episode\/11",
            "title": "The Land Where a Hero Once Lived",
            "title_japanese": "\u82f1\u96c4\u306e\u3044\u305f\u56fd",
            "title_romanji": "Eiyuu no ita Kuni\u00a0",
            "aired": "2002-12-12T00:00:00+00:00",
            "score": 4.1,
            "filler": false,
            "recap": false,
            "forum_url": "https:\/\/myanimelist.net\/forum\/?topicid=45114"
        },
        {
            "mal_id": 12,
            "url": "https:\/\/myanimelist.net\/anime\/20\/Naruto\/episode\/12",
            "title": "Battle on the Bridge! Zabuza Returns!!",
            "title_japanese": "\u6a4b\u4e0a\u6c7a\u6226!\u30b6\u30d6\u30b6\u518d\u3073!!",
            "title_romanji": "Kyoijou Kessen! Zabuza Futatabi!!\u00a0",
            "aired": "2002-12-19T00:00:00+00:00",
            "score": 4.1,
            "filler": false,
            "recap": false,
            "forum_url": "https:\/\/myanimelist.net\/forum\/?topicid=46344"
        },
        {
            "mal_id": 13,
            "url": "https:\/\/myanimelist.net\/anime\/20\/Naruto\/episode\/13",
            "title": "Haku's Secret Jutsu: Crystal Ice Mirrors",
            "title_japanese": "\u767d\u306e\u79d8\u8853 \u9b54\u93e1\u6c37\u6676",
            "title_romanji": "Haku no Hijutsu: Makyou Hyoushou\u00a0",
            "aired": "2002-12-26T00:00:00+00:00",
            "score": 4.3,
            "filler": false,
            "recap": false,
            "forum_url": "https:\/\/myanimelist.net\/forum\/?topicid=49695"
        },
        {
            "mal_id": 14,
            "url": "https:\/\/myanimelist.net\/anime\/20\/Naruto\/episode\/14",
            "title": "The Number One Hyperactive, Knucklehead Ninja Joins the Fight!!",
            "title_japanese": "\u610f\u5916\u6027No.1 \u30ca\u30eb\u30c8\u53c2\u6226!",
            "title_romanji": "Igaisei No. 1, Naruto Sansen!\u00a0",
            "aired": "2003-01-09T00:00:00+00:00",
            "score": 3.8,
            "filler": false,
            "recap": false,
            "forum_url": "https:\/\/myanimelist.net\/forum\/?topicid=52810"
        },
        {
            "mal_id": 15,
            "url": "https:\/\/myanimelist.net\/anime\/20\/Naruto\/episode\/15",
            "title": "Zero Visibility: The Sharingan Shatters",
            "title_japanese": "\u8996\u754c\u30bc\u30ed\u306e\u6226\u3044 \u5199\u8f2a\u773c\u5d29\u3057",
            "title_romanji": "Shikai Zero no Tatakai: Sharingan Kuzushi\u00a0",
            "aired": "2003-01-16T00:00:00+00:00",
            "score": 4,
            "filler": false,
            "recap": false,
            "forum_url": "https:\/\/myanimelist.net\/forum\/?topicid=102276"
        },
        {
            "mal_id": 16,
            "url": "https:\/\/myanimelist.net\/anime\/20\/Naruto\/episode\/16",
            "title": "The Broken Seal",
            "title_japanese": "\u89e3\u653e\u3055\u308c\u305f\u5c01\u5370",
            "title_romanji": "Kaihousareta Fuuin\u00a0",
            "aired": "2003-01-23T00:00:00+00:00",
            "score": 4.4,
            "filler": false,
            "recap": false,
            "forum_url": "https:\/\/myanimelist.net\/forum\/?topicid=102280"
        },
        {
            "mal_id": 17,
            "url": "https:\/\/myanimelist.net\/anime\/20\/Naruto\/episode\/17",
            "title": "White Past: Hidden Ambition",
            "title_japanese": "\u767d\u3044\u904e\u53bb\u30fb\u79d8\u3081\u305f\u60f3\u3044",
            "title_romanji": "Shiroi Kako: Himeta Omoi\u00a0",
            "aired": "2003-01-30T00:00:00+00:00",
            "score": 4.4,
            "filler": false,
            "recap": false,
            "forum_url": "https:\/\/myanimelist.net\/forum\/?topicid=102282"
        },
        {
            "mal_id": 18,
            "url": "https:\/\/myanimelist.net\/anime\/20\/Naruto\/episode\/18",
            "title": "The Weapons Known as Shinobi",
            "title_japanese": "\u5fcd\u3068\u3044\u3046\u540d\u306e\u9053\u5177",
            "title_romanji": "Shinobi to iu na no Dougu\u00a0",
            "aired": "2003-02-06T00:00:00+00:00",
            "score": 4.3,
            "filler": false,
            "recap": false,
            "forum_url": "https:\/\/myanimelist.net\/forum\/?topicid=102290"
        },
        {
            "mal_id": 19,
            "url": "https:\/\/myanimelist.net\/anime\/20\/Naruto\/episode\/19",
            "title": "The Demon in the Snow",
            "title_japanese": "\u30b6\u30d6\u30b6\u96ea\u306b\u6563\u308b\u2026",
            "title_romanji": "Zabuza Yuki ni Chiru...\u00a0",
            "aired": "2003-02-13T00:00:00+00:00",
            "score": 4.7,
            "filler": false,
            "recap": false,
            "forum_url": "https:\/\/myanimelist.net\/forum\/?topicid=60365"
        },
        {
            "mal_id": 20,
            "url": "https:\/\/myanimelist.net\/anime\/20\/Naruto\/episode\/20",
            "title": "A New Chapter Begins: The Chunin Exam!",
            "title_japanese": "\u65b0\u7ae0\u7a81\u5165!\u4e2d\u5fcd\u8a66\u9a13\u3060\u3063\u3066\u3070\u3088",
            "title_romanji": "Shinshou Totsunyuu! Chuunin Shiken Dattebayo\u00a0",
            "aired": "2003-02-20T00:00:00+00:00",
            "score": 4,
            "filler": false,
            "recap": false,
            "forum_url": "https:\/\/myanimelist.net\/forum\/?topicid=60468"
        },
        {
            "mal_id": 21,
            "url": "https:\/\/myanimelist.net\/anime\/20\/Naruto\/episode\/21",
            "title": "Identify Yourself: Powerful New Rivals",
            "title_japanese": "\u540d\u4e57\u308c!\u73fe\u308c\u305f\u5f37\u6575\u305f\u3061!!",
            "title_romanji": "Nanore! Arawareta Kyouteki-tachi!!\u00a0",
            "aired": "2003-02-27T00:00:00+00:00",
            "score": 4.1,
            "filler": false,
            "recap": false,
            "forum_url": "https:\/\/myanimelist.net\/forum\/?topicid=102587"
        },
        {
            "mal_id": 22,
            "url": "https:\/\/myanimelist.net\/anime\/20\/Naruto\/episode\/22",
            "title": "Chunin Challenge: Rock Lee vs. Sasuke!",
            "title_japanese": "\u6c17\u5408\u3044120% \u30ca\u30a6\u3067\u30ed\u30c3\u30af\u306a\u6311\u6226\u72b6!",
            "title_romanji": "Kiai 120% Nau de Rock na Chousenjou!\u00a0",
            "aired": "2003-03-06T00:00:00+00:00",
            "score": 4.2,
            "filler": false,
            "recap": false,
            "forum_url": "https:\/\/myanimelist.net\/forum\/?topicid=55858"
        },
        {
            "mal_id": 23,
            "url": "https:\/\/myanimelist.net\/anime\/20\/Naruto\/episode\/23",
            "title": "Genin Takedown! All Nine Rookies Face Off!",
            "title_japanese": "\u8e74\u6563\u3089\u305b\u30e9\u30a4\u30d0\u30eb!\u65b0\u4eba9\u4eba[\u30eb\u30fc\u30ad\u30fc\u30ca\u30a4\u30f3]\u5168\u54e1\u96c6\u5408",
            "title_romanji": "Kechirase Rival! Rookie 9 Zenin Shuugou\u00a0",
            "aired": "2003-03-13T00:00:00+00:00",
            "score": 4,
            "filler": false,
            "recap": false,
            "forum_url": "https:\/\/myanimelist.net\/forum\/?topicid=55884"
        },
        {
            "mal_id": 24,
            "url": "https:\/\/myanimelist.net\/anime\/20\/Naruto\/episode\/24",
            "title": "Start Your Engines: The Chunin Exam Begins!",
            "title_japanese": "\u3044\u304d\u306a\u308a\u5931\u683c?\u8d85\u96e3\u95a2\u306e\u7b2c\u4e00\u8a66\u9a13",
            "title_romanji": "Ikinari Shikkaku? Chou-nankan no Daiichi Shike\u00a0",
            "aired": "2003-03-20T00:00:00+00:00",
            "score": 4.4,
            "filler": false,
            "recap": false,
            "forum_url": "https:\/\/myanimelist.net\/forum\/?topicid=55919"
        },
        {
            "mal_id": 25,
            "url": "https:\/\/myanimelist.net\/anime\/20\/Naruto\/episode\/25",
            "title": "The Tenth Question: All or Nothing!",
            "title_japanese": "\u51fa\u305f\u3068\u3053\u52dd\u8ca0!\u8e0f\u3093\u5f35\u308a\u3069\u3053\u308d\u306e10\u554f\u76ee",
            "title_romanji": "Detatoko Shoubu! Funbaridokoro no Juu Monme\u00a0",
            "aired": "2003-03-27T00:00:00+00:00",
            "score": 4.4,
            "filler": false,
            "recap": false,
            "forum_url": "https:\/\/myanimelist.net\/forum\/?topicid=56153"
        },
        {
            "mal_id": 26,
            "url": "https:\/\/myanimelist.net\/anime\/20\/Naruto\/episode\/26",
            "title": "Special Report: Live from the Forest of Death!",
            "title_japanese": "\u7d76\u5bfe\u5fc5\u898b!\u6b7b\u306e\u68ee\u76f4\u524d\u30eb\u30dd!\u6728\u30ce\u8449\u306e\u5b66\u7d1a\u65b0\u805e\u3060\u30b3\u30ec!",
            "title_romanji": "Zettai Hikken! Shi no Mori Chokusen Rupo! Konoha no Gakkyuu Shinbun da Kore!\u00a0",
            "aired": "2003-04-02T00:00:00+00:00",
            "score": 2.7,
            "filler": false,
            "recap": true,
            "forum_url": "https:\/\/myanimelist.net\/forum\/?topicid=56509"
        },
        {
            "mal_id": 27,
            "url": "https:\/\/myanimelist.net\/anime\/20\/Naruto\/episode\/27",
            "title": "The Chunin Exam Stage 2: The Forest of Death",
            "title_japanese": "\u7b2c\u4e8c\u8a66\u9a13\u30b9\u30bf\u30fc\u30c8!\u5468\u308a\u306f\u307f\u3093\u306a\u6575\u3060\u3089\u3051!",
            "title_romanji": "Daini Shiken Start! Mawari wa Minna Teki Darake!\u00a0",
            "aired": "2003-04-02T00:00:00+00:00",
            "score": 4.1,
            "filler": false,
            "recap": false,
            "forum_url": "https:\/\/myanimelist.net\/forum\/?topicid=56512"
        },
        {
            "mal_id": 28,
            "url": "https:\/\/myanimelist.net\/anime\/20\/Naruto\/episode\/28",
            "title": "Eat or be Eaten: Panic in the Forest",
            "title_japanese": "\u55b0\u3046\u304b\u55b0\u308f\u308c\u308b\u304b!\u30a8\u30b5\u306b\u306a\u3063\u305f\u30ca\u30eb\u30c8",
            "title_romanji": "Kuu ka Kuwareru ka! Esa ni Natta Naruto\u00a0",
            "aired": "2003-04-09T00:00:00+00:00",
            "score": 4.5,
            "filler": false,
            "recap": false,
            "forum_url": "https:\/\/myanimelist.net\/forum\/?topicid=56677"
        },
        {
            "mal_id": 29,
            "url": "https:\/\/myanimelist.net\/anime\/20\/Naruto\/episode\/29",
            "title": "Naruto's Counterattack: Never Give In!",
            "title_japanese": "\u30ca\u30eb\u30c8\u53cd\u6483!\u9003\u3052\u306d\u30fc\u3093\u3060\u3063\u3066\u3070\u3088!",
            "title_romanji": "Naruto Hangeki! Nigeneenn Dattebayo!\u00a0",
            "aired": "2003-04-16T00:00:00+00:00",
            "score": 4.4,
            "filler": false,
            "recap": false,
            "forum_url": "https:\/\/myanimelist.net\/forum\/?topicid=56946"
        },
        {
            "mal_id": 30,
            "url": "https:\/\/myanimelist.net\/anime\/20\/Naruto\/episode\/30",
            "title": "The Sharingan Revived: Dragon-Flame Jutsu!",
            "title_japanese": "\u8607\u308c\u5199\u8f2a\u773c!\u5fc5\u6bba\u30fb\u706b\u9041\u9f8d\u706b\u306e\u8853!",
            "title_romanji": "Yomigaere Sharingan! Hissatsu: Katon Ryuuka no Jutsu!\u00a0",
            "aired": "2003-04-23T00:00:00+00:00",
            "score": 4.5,
            "filler": false,
            "recap": false,
            "forum_url": "https:\/\/myanimelist.net\/forum\/?topicid=57071"
        },
        {
            "mal_id": 31,
            "url": "https:\/\/myanimelist.net\/anime\/20\/Naruto\/episode\/31",
            "title": "Bushy Brow's Pledge: Undying Love and Protection!",
            "title_japanese": "\u6fc0\u307e\u3086\u30d7\u30e9\u30c8\u30cb\u30c3\u30af!\u50d5\u306f\u6b7b\u306c\u307e\u3067\u30a2\u30ca\u30bf\u3092\u5b88\u308b!!",
            "title_romanji": "Geki Mayu Platonic! Boku wa Shinu Made Anata wo Mamoru!!\u00a0",
            "aired": "2003-04-30T00:00:00+00:00",
            "score": 4.3,
            "filler": false,
            "recap": false,
            "forum_url": "https:\/\/myanimelist.net\/forum\/?topicid=60644"
        },
        {
            "mal_id": 32,
            "url": "https:\/\/myanimelist.net\/anime\/20\/Naruto\/episode\/32",
            "title": "Sakura Blossoms!",
            "title_japanese": "\u30b5\u30af\u30e9\u54b2\u304f!\u6c7a\u610f\u306e\u5f8c\u308d\u59ff",
            "title_romanji": "Sakura Saku! Ketsui no Ushiro Sugata\u00a0",
            "aired": "2003-05-07T00:00:00+00:00",
            "score": 4.3,
            "filler": false,
            "recap": false,
            "forum_url": "https:\/\/myanimelist.net\/forum\/?topicid=60655"
        },
        {
            "mal_id": 33,
            "url": "https:\/\/myanimelist.net\/anime\/20\/Naruto\/episode\/33",
            "title": "Battle Formation: Ino-Shika-Cho!",
            "title_japanese": "\u7121\u6575\u306e\u30d5\u30a9\u30fc\u30e1\u30fc\u30b7\u30e7\u30f3!\u3044\u306e\u30b7\u30ab\u30c1\u30e7\u30a6!!",
            "title_romanji": "Muteki no Fomation! Ino-Shika-Chou!!\u00a0",
            "aired": "2003-05-14T00:00:00+00:00",
            "score": 4.4,
            "filler": false,
            "recap": false,
            "forum_url": "https:\/\/myanimelist.net\/forum\/?topicid=99208"
        },
        {
            "mal_id": 34,
            "url": "https:\/\/myanimelist.net\/anime\/20\/Naruto\/episode\/34",
            "title": "Akamaru Trembles: Gaara's Cruel Strength!",
            "title_japanese": "\u8d64\u4e38\u30d3\u30c3\u30af\u30ea!\u6211\u611b\u7f85, \u9a5a\u7570\u306e\u5b9f\u529b",
            "title_romanji": "Akamaru Bikkuri! Gaara, Kyoui no Jitsuryoku\u00a0",
            "aired": "2003-05-21T00:00:00+00:00",
            "score": 4.3,
            "filler": false,
            "recap": false,
            "forum_url": "https:\/\/myanimelist.net\/forum\/?topicid=99317"
        },
        {
            "mal_id": 35,
            "url": "https:\/\/myanimelist.net\/anime\/20\/Naruto\/episode\/35",
            "title": "The Scroll's Secret: No Peeking Allowed",
            "title_japanese": "\u306e\u305e\u304d\u898b\u53b3\u7981!\u5dfb\u304d\u7269\u306e\u79d8\u5bc6",
            "title_romanji": "Nozokimi Genkin! Makimono no Himitsu\u00a0",
            "aired": "2003-05-28T00:00:00+00:00",
            "score": 4,
            "filler": false,
            "recap": false,
            "forum_url": "https:\/\/myanimelist.net\/forum\/?topicid=99405"
        },
        {
            "mal_id": 36,
            "url": "https:\/\/myanimelist.net\/anime\/20\/Naruto\/episode\/36",
            "title": "Clone vs. Clone: Mine are Better than Yours!",
            "title_japanese": "\u5206\u8eab\u5bfe\u6c7a!\u30aa\u30ec\u304c\u4e3b\u5f79\u3060\u3063\u3066\u3070\u3088!",
            "title_romanji": "Bunshin Taiketsu! Ore ga Shuyaku Dattebayo!\u00a0",
            "aired": "2003-06-04T00:00:00+00:00",
            "score": 4.2,
            "filler": false,
            "recap": false,
            "forum_url": "https:\/\/myanimelist.net\/forum\/?topicid=99604"
        },
        {
            "mal_id": 37,
            "url": "https:\/\/myanimelist.net\/anime\/20\/Naruto\/episode\/37",
            "title": "Surviving the Cut! The Rookie Nine Together Again!",
            "title_japanese": "\u7b2c\u4e8c\u8a66\u9a13\u7a81\u7834!\u52e2\u305e\u308d\u3044\u30eb\u30fc\u30ad\u30fc\u30ca\u30a4\u30f3!",
            "title_romanji": "Daini Shiken Toppa! Seizoroi Rookie Nine!\u00a0",
            "aired": "2003-06-11T00:00:00+00:00",
            "score": 4.1,
            "filler": false,
            "recap": false,
            "forum_url": "https:\/\/myanimelist.net\/forum\/?topicid=100214"
        },
        {
            "mal_id": 38,
            "url": "https:\/\/myanimelist.net\/anime\/20\/Naruto\/episode\/38",
            "title": "Narrowing the Field: Sudden Death Elimination!",
            "title_japanese": "\u5408\u683c\u8005\u4e8c\u5206\u306e\u4e00!?\u30a4\u30ad\u30ca\u30ea\u8a66\u5408\u3060\u3063\u3066\u3070\u3088!!",
            "title_romanji": "Goukakusha Nibun ni Ichi!? Ikinari Shiai Dattebayo!!\u00a0",
            "aired": "2003-06-18T00:00:00+00:00",
            "score": 4.3,
            "filler": false,
            "recap": false,
            "forum_url": "https:\/\/myanimelist.net\/forum\/?topicid=100217"
        },
        {
            "mal_id": 39,
            "url": "https:\/\/myanimelist.net\/anime\/20\/Naruto\/episode\/39",
            "title": "Bushy Brow's Jealousy: Lions Barrage Unleashed!",
            "title_japanese": "\u30b2\u30b8\u307e\u3086\u30b8\u30a7\u30e9\u30b7\u30fc!\u300c\u7345\u5b50\u9023\u5f3e\u300d\u8a95\u751f!",
            "title_romanji": "Geji Mayu Jealousy! Shishi Rendan Tanjou\u00a0",
            "aired": "2003-07-02T00:00:00+00:00",
            "score": 4.5,
            "filler": false,
            "recap": false,
            "forum_url": "https:\/\/myanimelist.net\/forum\/?topicid=100256"
        },
        {
            "mal_id": 40,
            "url": "https:\/\/myanimelist.net\/anime\/20\/Naruto\/episode\/40",
            "title": "Kakashi and Orochimaru: Face-to-Face!",
            "title_japanese": "\u4e00\u89e6\u5373\u767a!!\u30ab\u30ab\u30b7VS\u5927\u86c7\u4e38",
            "title_romanji": "Isshoku Sokuhatsu!! Kakashi vs Orochimaru\u00a0",
            "aired": "2003-07-09T00:00:00+00:00",
            "score": 4.2,
            "filler": false,
            "recap": false,
            "forum_url": "https:\/\/myanimelist.net\/forum\/?topicid=87203"
        },
        {
            "mal_id": 41,
            "url": "https:\/\/myanimelist.net\/anime\/20\/Naruto\/episode\/41",
            "title": "Kunoichi Rumble: The Rivals Get Serious!",
            "title_japanese": "\u30e9\u30a4\u30d0\u30eb\u6fc0\u7a81!\u30aa\u30c8\u30e1\u5fc3\u306f\u672c\u6c17\u30e2\u30fc\u30c9",
            "title_romanji": "Rival Gekitotsu! Otomegokoro wa Honki Mode\u00a0",
            "aired": "2003-07-16T00:00:00+00:00",
            "score": 3.7,
            "filler": false,
            "recap": false,
            "forum_url": "https:\/\/myanimelist.net\/forum\/?topicid=102831"
        },
        {
            "mal_id": 42,
            "url": "https:\/\/myanimelist.net\/anime\/20\/Naruto\/episode\/42",
            "title": "The Ultimate Battle: Cha!",
            "title_japanese": "\u30d9\u30b9\u30c8\u30d0\u30c8\u30eb\u306f\u3057\u3083\u30fc\u3093\u306a\u308d\u30fc!!",
            "title_romanji": "Best Battle wa Shaannaroo!!\u00a0",
            "aired": "2003-07-23T00:00:00+00:00",
            "score": 3.8,
            "filler": false,
            "recap": false,
            "forum_url": "https:\/\/myanimelist.net\/forum\/?topicid=102836"
        },
        {
            "mal_id": 43,
            "url": "https:\/\/myanimelist.net\/anime\/20\/Naruto\/episode\/43",
            "title": "Killer Kunoichi and a Shaky Shikamaru",
            "title_japanese": "\u30b7\u30ab\u30de\u30eb\u30bf\u30b8\u30bf\u30b8!?\u304f\u306e\u4e00\u9054\u306e\u71b1\u304d\u6226\u3044",
            "title_romanji": "Shikamaru Tajitaji!? Kunoichi-tachi no Atsuki Tatakai\u00a0",
            "aired": "2003-07-30T00:00:00+00:00",
            "score": 4.3,
            "filler": false,
            "recap": false,
            "forum_url": "https:\/\/myanimelist.net\/forum\/?topicid=102842"
        },
        {
            "mal_id": 44,
            "url": "https:\/\/myanimelist.net\/anime\/20\/Naruto\/episode\/44",
            "title": "Akamaru Unleashed! Who's Top Dog Now?",
            "title_japanese": "\u8d64\u4e38\u53c2\u6226!!\u8ca0\u3051\u72ac\u306f\u3069\u3063\u3061\u3060?",
            "title_romanji": "Akamaru Sansen! Makeinu wa Docchi da?\u00a0",
            "aired": "2003-08-06T00:00:00+00:00",
            "score": 4.4,
            "filler": false,
            "recap": false,
            "forum_url": "https:\/\/myanimelist.net\/forum\/?topicid=102851"
        },
        {
            "mal_id": 45,
            "url": "https:\/\/myanimelist.net\/anime\/20\/Naruto\/episode\/45",
            "title": "Surprise Attack! Naruto's Secret Weapon!",
            "title_japanese": "\u30d2\u30ca\u30bf\u8d64\u9762! \u89b3\u5ba2\u3042\u3093\u3050\u308a, \u30ca\u30eb\u30c8\u306e\u5965\u306e\u624b",
            "title_romanji": "Hinata Sekimen! Kankyaku Anguri, Naruto no Oku no te\u00a0",
            "aired": "2003-08-13T00:00:00+00:00",
            "score": 4.3,
            "filler": false,
            "recap": false,
            "forum_url": "https:\/\/myanimelist.net\/forum\/?topicid=102855"
        },
        {
            "mal_id": 46,
            "url": "https:\/\/myanimelist.net\/anime\/20\/Naruto\/episode\/46",
            "title": "Byakugan Battle: Hinata Grows Bold!",
            "title_japanese": "\u767d\u773c\u958b\u773c!!\u5185\u6c17\u306a\u30d2\u30ca\u30bf\u306e\u5927\u80c6\u6c7a\u610f!",
            "title_romanji": "Byakugan Kaigen!! Uchiki na Hinata no Daitan Ketsui!\u00a0",
            "aired": "2003-08-20T00:00:00+00:00",
            "score": 4.4,
            "filler": false,
            "recap": false,
            "forum_url": "https:\/\/myanimelist.net\/forum\/?topicid=102867"
        },
        {
            "mal_id": 47,
            "url": "https:\/\/myanimelist.net\/anime\/20\/Naruto\/episode\/47",
            "title": "A Failure Stands Tall!",
            "title_japanese": "\u61a7\u308c\u306e\u4eba\u306e\u76ee\u306e\u524d\u3067!!",
            "title_romanji": "Akogare no Hito no me no mae de!!\u00a0",
            "aired": "2003-08-27T00:00:00+00:00",
            "score": 4.6,
            "filler": false,
            "recap": false,
            "forum_url": "https:\/\/myanimelist.net\/forum\/?topicid=102871"
        },
        {
            "mal_id": 48,
            "url": "https:\/\/myanimelist.net\/anime\/20\/Naruto\/episode\/48",
            "title": "Gaara vs. Rock Lee: The Power of Youth Explodes!",
            "title_japanese": "\u6211\u611b\u7f85\u7c89\u7815!!\u82e5\u3055\u3060!\u30d1\u30ef\u30fc\u3060!\u7206\u767a\u3060!",
            "title_romanji": "Gaara Funsai!! Wakasa da! Power da! Bakuhatsu da!\u00a0",
            "aired": "2003-09-03T00:00:00+00:00",
            "score": 4.8,
            "filler": false,
            "recap": false,
            "forum_url": "https:\/\/myanimelist.net\/forum\/?topicid=102882"
        },
        {
            "mal_id": 49,
            "url": "https:\/\/myanimelist.net\/anime\/20\/Naruto\/episode\/49",
            "title": "Lee's Hidden Strength: Forbidden Secret Jutsu!",
            "title_japanese": "\u71b1\u8840\u843d\u3061\u3053\u307c\u308c!\u9042\u306b\u70b8\u88c2, \u7981\u65ad\u306e\u5965\u7fa9!",
            "title_romanji": "Nekketsu Ochikobore! Tsuini Sakuretsu, Kindan no Oogi!\u00a0",
            "aired": "2003-09-10T00:00:00+00:00",
            "score": 4.7,
            "filler": false,
            "recap": false,
            "forum_url": "https:\/\/myanimelist.net\/forum\/?topicid=102890"
        },
        {
            "mal_id": 50,
            "url": "https:\/\/myanimelist.net\/anime\/20\/Naruto\/episode\/50",
            "title": "The Fifth Gate: A Splendid Ninja is Born",
            "title_japanese": "\u55da\u547c\u30ed\u30c3\u30af\u00b7\u30ea\u30fc!\u3053\u308c\u304c\u7537\u306e\u751f\u304d\u69d8\u3088!!",
            "title_romanji": "Aa Rock Lee! Kore ga Otoko no Ikizama yo!!\u00a0",
            "aired": "2003-09-17T00:00:00+00:00",
            "score": 4.6,
            "filler": false,
            "recap": false,
            "forum_url": "https:\/\/myanimelist.net\/forum\/?topicid=103009"
        },
        {
            "mal_id": 51,
            "url": "https:\/\/myanimelist.net\/anime\/20\/Naruto\/episode\/51",
            "title": "A Shadow in Darkness: Danger Approaches Sasuke",
            "title_japanese": "\u95c7\u306b\u3046\u3054\u3081\u304f\u5f71 \u30b5\u30b9\u30b1\u306b\u8feb\u308b\u5371\u6a5f!",
            "title_romanji": "Yami ni Ugomeku Kage Sasuke ni Semaru Kiki!\u00a0",
            "aired": "2003-09-24T00:00:00+00:00",
            "score": 4.2,
            "filler": false,
            "recap": false,
            "forum_url": "https:\/\/myanimelist.net\/forum\/?topicid=103015"
        },
        {
            "mal_id": 52,
            "url": "https:\/\/myanimelist.net\/anime\/20\/Naruto\/episode\/52",
            "title": "Ebisu Returns: Naruto's Toughest Training Yet!",
            "title_japanese": "\u30a8\u30d3\u30b9\u518d\u3073!\u30cf\u30ec\u30f3\u30c1\u306f\u79c1\u304c\u8a31\u3057\u307e\u305b\u3093\u305e!",
            "title_romanji": "Ebisu Futatabi! Harenchi wa Watashi ga Yurushimasen zo!\u00a0",
            "aired": "2003-10-01T00:00:00+00:00",
            "score": 4.2,
            "filler": false,
            "recap": false,
            "forum_url": "https:\/\/myanimelist.net\/forum\/?topicid=103020"
        },
        {
            "mal_id": 53,
            "url": "https:\/\/myanimelist.net\/anime\/20\/Naruto\/episode\/53",
            "title": "Long Time No See: Jiraiya Returns!",
            "title_japanese": "\u3042\u3044\u3084\u3057\u3070\u3089\u304f!\u30a8\u30ed\u4ed9\u4eba\u767b\u5834!",
            "title_romanji": "Aiyashibaraku! Ero-sennin Toujou!\u00a0",
            "aired": "2003-10-08T00:00:00+00:00",
            "score": 4.3,
            "filler": false,
            "recap": false,
            "forum_url": "https:\/\/myanimelist.net\/forum\/?topicid=103030"
        },
        {
            "mal_id": 54,
            "url": "https:\/\/myanimelist.net\/anime\/20\/Naruto\/episode\/54",
            "title": "The Summoning Jutsu: Wisdom of the Toad Sage!",
            "title_japanese": "\u30a8\u30ed\u4ed9\u4eba\u76f4\u4f1d \u53e3\u5bc4\u305b\u306e\u8853\u3060\u3063\u3066\u3070\u3088!!",
            "title_romanji": "Ero-sennin Jikiden Kuchiyose no Jutsu Dattebayo!!\u00a0",
            "aired": "2003-10-15T00:00:00+00:00",
            "score": 4.2,
            "filler": false,
            "recap": false,
            "forum_url": "https:\/\/myanimelist.net\/forum\/?topicid=103037"
        },
        {
            "mal_id": 55,
            "url": "https:\/\/myanimelist.net\/anime\/20\/Naruto\/episode\/55",
            "title": "A Feeling of Yearning, A Flower Full of Hope",
            "title_japanese": "\u5207\u306a\u3044\u60f3\u3044 \u9858\u3044\u3092\u8fbc\u3081\u305f\u4e00\u8f2a",
            "title_romanji": "Setsunai Omoi Negai wo Kometa Ichirin\u00a0",
            "aired": "2003-10-22T00:00:00+00:00",
            "score": 4.2,
            "filler": false,
            "recap": false,
            "forum_url": "https:\/\/myanimelist.net\/forum\/?topicid=103045"
        },
        {
            "mal_id": 56,
            "url": "https:\/\/myanimelist.net\/anime\/20\/Naruto\/episode\/56",
            "title": "Live or Die: Risk it All to Win it All!",
            "title_japanese": "\u751f\u304b\u6b7b\u304b!?\u514d\u8a31\u7686\u4f1d\u306f\u547d\u61f8\u3051!",
            "title_romanji": "Sei ka Shi ka!? Menkyokaiden wa Inochigake!\u00a0",
            "aired": "2003-10-29T00:00:00+00:00",
            "score": 4.4,
            "filler": false,
            "recap": false,
            "forum_url": "https:\/\/myanimelist.net\/forum\/?topicid=103064"
        },
        {
            "mal_id": 57,
            "url": "https:\/\/myanimelist.net\/anime\/20\/Naruto\/episode\/57",
            "title": "He Flies! He Jumps! He Lurks! Chief Toad Appears!",
            "title_japanese": "\u98db\u3093\u3060!\u8df3\u306d\u305f!\u6f5c\u3063\u305f!\u30ac\u30de\u89aa\u5206\u767b\u5834!!",
            "title_romanji": "Tonda! Haneta! Mogutta! Gama Oyabun Toujou!!\u00a0",
            "aired": "2003-11-05T00:00:00+00:00",
            "score": 4.4,
            "filler": false,
            "recap": false,
            "forum_url": "https:\/\/myanimelist.net\/forum\/?topicid=103066"
        },
        {
            "mal_id": 58,
            "url": "https:\/\/myanimelist.net\/anime\/20\/Naruto\/episode\/58",
            "title": "Hospital Besieged: The Evil Hand Revealed!",
            "title_japanese": "\u3057\u306e\u3073\u5bc4\u308b\u9b54\u306e\u624b!\u72d9\u308f\u308c\u305f\u75c5\u5ba4",
            "title_romanji": "Shinobiyoru ma no te! Nerawareta Byoushitsu\u00a0",
            "aired": "2003-11-12T00:00:00+00:00",
            "score": 4.3,
            "filler": false,
            "recap": false,
            "forum_url": "https:\/\/myanimelist.net\/forum\/?topicid=103069"
        },
        {
            "mal_id": 59,
            "url": "https:\/\/myanimelist.net\/anime\/20\/Naruto\/episode\/59",
            "title": "The Final Rounds: Rush to the Battle Arena!",
            "title_japanese": "\u30e2\u30fc\u70c8 \u30e2\u30fc\u8ffd \u30e2\u30fc\u30c0\u30c3\u30b7\u30e5 \u672c\u9078\u958b\u59cb\u3060\u3063\u3066\u3070\u3088",
            "title_romanji": "Mou Retsu Mou Tsui Mou Dasshu Hansen Kaishi Dattebayo\u00a0",
            "aired": "2003-11-19T00:00:00+00:00",
            "score": 4.2,
            "filler": false,
            "recap": false,
            "forum_url": "https:\/\/myanimelist.net\/forum\/?topicid=103076"
        },
        {
            "mal_id": 60,
            "url": "https:\/\/myanimelist.net\/anime\/20\/Naruto\/episode\/60",
            "title": "Byakugan vs. Shadow Clone",
            "title_japanese": "\u767d\u773cVS\u5f71\u5206\u8eab!\u30aa\u30ec\u306f\u30bc\u3063\u3066\u30fc\u52dd\u3064!!",
            "title_romanji": "Byakugan vs Kage Bunshin! Ore wa Zettee Katsu!!\u00a0",
            "aired": "2003-11-26T00:00:00+00:00",
            "score": 4.2,
            "filler": false,
            "recap": false,
            "forum_url": "https:\/\/myanimelist.net\/forum\/?topicid=103083"
        },
        {
            "mal_id": 61,
            "url": "https:\/\/myanimelist.net\/anime\/20\/Naruto\/episode\/61",
            "title": "Ultimate Defense: Zero Blind Spot!",
            "title_japanese": "\u6b7b\u89d2\u30bc\u30ed!\u3082\u3046\u3072\u3068\u3064\u306e\u7d76\u5bfe\u9632\u5fa1",
            "title_romanji": "Shikaku Zero! Mou Hitotsu no Zettai Bougyo\u00a0",
            "aired": "2003-12-03T00:00:00+00:00",
            "score": 4.4,
            "filler": false,
            "recap": false,
            "forum_url": "https:\/\/myanimelist.net\/forum\/?topicid=103266"
        },
        {
            "mal_id": 62,
            "url": "https:\/\/myanimelist.net\/anime\/20\/Naruto\/episode\/62",
            "title": "A Failure's True Power",
            "title_japanese": "\u843d\u3061\u3053\u307c\u308c\u306e\u5e95\u529b!",
            "title_romanji": "Ochikobore no Sokojikara!\u00a0",
            "aired": "2003-12-10T00:00:00+00:00",
            "score": 4.5,
            "filler": false,
            "recap": false,
            "forum_url": "https:\/\/myanimelist.net\/forum\/?topicid=103268"
        },
        {
            "mal_id": 63,
            "url": "https:\/\/myanimelist.net\/anime\/20\/Naruto\/episode\/63",
            "title": "Hit it or Quit it: The Final Rounds Get Complicated!",
            "title_japanese": "\u5931\u683c!?\u30ad\u30b1\u30f3!\u524d\u5012\u3057!\u6ce2\u4e71\u542b\u307f\u306e\u5927\u672c\u6226",
            "title_romanji": "Shikkaku!? Kiken! Maedaoshi! Haranbukumi no Daihonsen!\u00a0",
            "aired": "2003-12-17T00:00:00+00:00",
            "score": 4.2,
            "filler": false,
            "recap": false,
            "forum_url": "https:\/\/myanimelist.net\/forum\/?topicid=103327"
        },
        {
            "mal_id": 64,
            "url": "https:\/\/myanimelist.net\/anime\/20\/Naruto\/episode\/64",
            "title": "Zero Motivation: The Guy with Cloud Envy!",
            "title_japanese": "\u96f2\u306f\u3044\u3044\u306a\u3042...\u3084\u308b\u6c17\u30bc\u30ed\u306e\u7537",
            "title_romanji": "Kumo wa ii naa... Yaruki Zero no Otoko\u00a0",
            "aired": "2003-12-24T00:00:00+00:00",
            "score": 4.5,
            "filler": false,
            "recap": false,
            "forum_url": "https:\/\/myanimelist.net\/forum\/?topicid=103397"
        },
        {
            "mal_id": 65,
            "url": "https:\/\/myanimelist.net\/anime\/20\/Naruto\/episode\/65",
            "title": "Dancing Leaf, Squirming Sand",
            "title_japanese": "\u6fc0\u7a81!\u6728\u30ce\u8449\u821e\u3044\u7802\u3046\u3054\u3081\u304f\u77ac\u9593",
            "title_romanji": "Gekitotsu! Konoha mai Suna Ugomeku Toki\u00a0",
            "aired": "2003-12-31T00:00:00+00:00",
            "score": 4.1,
            "filler": false,
            "recap": false,
            "forum_url": "https:\/\/myanimelist.net\/forum\/?topicid=103519"
        },
        {
            "mal_id": 66,
            "url": "https:\/\/myanimelist.net\/anime\/20\/Naruto\/episode\/66",
            "title": "Bushy Brow's Jutsu: Sasuke Style!",
            "title_japanese": "\u5d50\u3092\u547c\u3076\u7537!!\u30b5\u30b9\u30b1\u306e\u30b2\u30b8\u30de\u30e6\u6d41\u4f53\u8853!",
            "title_romanji": "Arashi wo Yobu Otoko!! Sasuke no Gejimayu-ryuu Taijutsu!\u00a0",
            "aired": "2004-01-14T00:00:00+00:00",
            "score": 4.3,
            "filler": false,
            "recap": false,
            "forum_url": "https:\/\/myanimelist.net\/forum\/?topicid=103551"
        },
        {
            "mal_id": 67,
            "url": "https:\/\/myanimelist.net\/anime\/20\/Naruto\/episode\/67",
            "title": "Late for the Show, But Ready to Go! The Ultimate Secret Technique is Born!",
            "title_japanese": "\u3060\u3066\u306b\u9045\u308c\u305f\u308f\u3051\u3058\u3083\u306a\u3044!\u7a76\u6975\u5965\u7fa9\u00b7\u5343\u9ce5\u8a95\u751f!!",
            "title_romanji": "Date ni Okureta Wake ja nai! Kyuukyoku Ougi: Chidori Tanjou!!\u00a0",
            "aired": "2004-01-14T00:00:00+00:00",
            "score": 4.5,
            "filler": false,
            "recap": false,
            "forum_url": "https:\/\/myanimelist.net\/forum\/?topicid=103557"
        },
        {
            "mal_id": 68,
            "url": "https:\/\/myanimelist.net\/anime\/20\/Naruto\/episode\/68",
            "title": "Zero Hour! The Destruction of the Hidden Leaf Village Begins!",
            "title_japanese": "\u300c\u6728\u30ce\u8449\u5d29\u3057\u300d\u59cb\u52d5!",
            "title_romanji": "Konoha Kuzushi Shidou!\u00a0",
            "aired": "2004-01-28T00:00:00+00:00",
            "score": 4.4,
            "filler": false,
            "recap": false,
            "forum_url": "https:\/\/myanimelist.net\/forum\/?topicid=103562"
        },
        {
            "mal_id": 69,
            "url": "https:\/\/myanimelist.net\/anime\/20\/Naruto\/episode\/69",
            "title": "Village in Distress: A New A-Ranked Mission!",
            "title_japanese": "\u5f85\u3063\u3066\u307e\u3057\u305f!A\u30e9\u30f3\u30af\u4efb\u52d9\u3060\u3063\u3066\u3070\u3088!!",
            "title_romanji": "Mattemashita! A-rank Ninmu Dattebayo!!\u00a0",
            "aired": "2004-02-04T00:00:00+00:00",
            "score": 4.4,
            "filler": false,
            "recap": false,
            "forum_url": "https:\/\/myanimelist.net\/forum\/?topicid=103575"
        },
        {
            "mal_id": 70,
            "url": "https:\/\/myanimelist.net\/anime\/20\/Naruto\/episode\/70",
            "title": "A Shirker's Call to Action: A Layabout No More!",
            "title_japanese": "\u9003\u3052\u8170NO.1 \u3081\u3093\u3069\u304f\u305b\u30fc\u304c\u3084\u308d\u3063\u304d\u3083\u306d\u3048!!",
            "title_romanji": "Nigegoshi NO.1 Mendokuse~ ga Yarukkya nee!!\u00a0",
            "aired": "2004-02-11T00:00:00+00:00",
            "score": 4.3,
            "filler": false,
            "recap": false,
            "forum_url": "https:\/\/myanimelist.net\/forum\/?topicid=103580"
        },
        {
            "mal_id": 71,
            "url": "https:\/\/myanimelist.net\/anime\/20\/Naruto\/episode\/71",
            "title": "An Unrivaled Match: Hokage Battle Royale!",
            "title_japanese": "\u53e4\u4eca\u7121\u53cc!\u300c\u706b\u5f71\u300d\u3068\u3044\u3046\u30ec\u30d9\u30eb\u306e\u6226\u3044",
            "title_romanji": "Kokon Musou! Hokage to iu Level no Tatakai\u00a0",
            "aired": "2004-02-18T00:00:00+00:00",
            "score": 4.4,
            "filler": false,
            "recap": false,
            "forum_url": "https:\/\/myanimelist.net\/forum\/?topicid=104202"
        },
        {
            "mal_id": 72,
            "url": "https:\/\/myanimelist.net\/anime\/20\/Naruto\/episode\/72",
            "title": "A Mistake from the Past: A Face Revealed!",
            "title_japanese": "\u706b\u5f71\u306e\u904e\u3061 \u4eee\u9762\u306e\u4e0b\u306e\u7d20\u9854",
            "title_romanji": "Hokage no Ayamachi Kamen ni shita no Sugao\u00a0",
            "aired": "2004-02-25T00:00:00+00:00",
            "score": 4.5,
            "filler": false,
            "recap": false,
            "forum_url": "https:\/\/myanimelist.net\/forum\/?topicid=104207"
        },
        {
            "mal_id": 73,
            "url": "https:\/\/myanimelist.net\/anime\/20\/Naruto\/episode\/73",
            "title": "Forbidden Secret Technique: Reaper Death Seal!",
            "title_japanese": "\u7981\u8853\u5965\u7fa9!\u300c\u5c4d\u9b3c\u5c01\u5c3d\u300d",
            "title_romanji": "Kinjutsu Ougi! Shiki Fuujin\u00a0",
            "aired": "2004-03-03T00:00:00+00:00",
            "score": 4.4,
            "filler": false,
            "recap": false,
            "forum_url": "https:\/\/myanimelist.net\/forum\/?topicid=104212"
        },
        {
            "mal_id": 74,
            "url": "https:\/\/myanimelist.net\/anime\/20\/Naruto\/episode\/74",
            "title": "Astonishing Truth! Gaara's Identity Emerges!",
            "title_japanese": "\u9a5a\u6115!\u6211\u611b\u7f85\u306e\u6b63\u4f53",
            "title_romanji": "Kyougaku! Gaara no Shoutai\u00a0",
            "aired": "2004-03-10T00:00:00+00:00",
            "score": 4.3,
            "filler": false,
            "recap": false,
            "forum_url": "https:\/\/myanimelist.net\/forum\/?topicid=104220"
        },
        {
            "mal_id": 75,
            "url": "https:\/\/myanimelist.net\/anime\/20\/Naruto\/episode\/75",
            "title": "Sasuke's Decision: Pushed to the Edge!",
            "title_japanese": "\u9650\u754c\u3092\u8d8a\u3048\u3066... \u30b5\u30b9\u30b1\u306e\u6c7a\u65ad!!",
            "title_romanji": "Genkai Wo Koete... Sasuke no Ketsudan!!\u00a0",
            "aired": "2004-03-17T00:00:00+00:00",
            "score": 4.4,
            "filler": false,
            "recap": false,
            "forum_url": "https:\/\/myanimelist.net\/forum\/?topicid=104237"
        },
        {
            "mal_id": 76,
            "url": "https:\/\/myanimelist.net\/anime\/20\/Naruto\/episode\/76",
            "title": "Assassin of the Moonlit Night",
            "title_japanese": "\u6708\u591c\u306e\u6697\u6bba\u8005",
            "title_romanji": "Tsukiyo no Ansatsusha\u00a0",
            "aired": "2004-03-24T00:00:00+00:00",
            "score": 4.5,
            "filler": false,
            "recap": false,
            "forum_url": "https:\/\/myanimelist.net\/forum\/?topicid=104240"
        },
        {
            "mal_id": 77,
            "url": "https:\/\/myanimelist.net\/anime\/20\/Naruto\/episode\/77",
            "title": "Light vs. Dark: The Two Faces of Gaara",
            "title_japanese": "\u5149\u3068\u95c7 \u6211\u611b\u7f85\u3068\u3044\u3046\u540d",
            "title_romanji": "Hikari to Yami Gaara to iu na\u00a0",
            "aired": "2004-03-31T00:00:00+00:00",
            "score": 4.3,
            "filler": false,
            "recap": false,
            "forum_url": "https:\/\/myanimelist.net\/forum\/?topicid=104247"
        },
        {
            "mal_id": 78,
            "url": "https:\/\/myanimelist.net\/anime\/20\/Naruto\/episode\/78",
            "title": "Naruto's Ninja Handbook",
            "title_japanese": "\u7206\u767a!\u3053\u308c\u305e\u30ca\u30eb\u30c8\u5fcd\u6cd5\u5e16\u301c\u301c\u3063!!",
            "title_romanji": "Bakuhatsu! Kore zo Naruto Ninpouchou~~!!\u00a0",
            "aired": "2004-04-07T00:00:00+00:00",
            "score": 4.7,
            "filler": false,
            "recap": false,
            "forum_url": "https:\/\/myanimelist.net\/forum\/?topicid=104253"
        },
        {
            "mal_id": 79,
            "url": "https:\/\/myanimelist.net\/anime\/20\/Naruto\/episode\/79",
            "title": "Beyond the Limit of Darkness and Light",
            "title_japanese": "\u30ea\u30df\u30c3\u30c8\u3076\u3063\u3061\u304e\u308a! \u301c\u5149\u3068\u95c7\u301c",
            "title_romanji": "Limit Bucchigiri!: Hikari to Yami\u00a0",
            "aired": "2004-04-14T00:00:00+00:00",
            "score": 4.6,
            "filler": false,
            "recap": false,
            "forum_url": "https:\/\/myanimelist.net\/forum\/?topicid=104421"
        },
        {
            "mal_id": 80,
            "url": "https:\/\/myanimelist.net\/anime\/20\/Naruto\/episode\/80",
            "title": "The Third Hokage, Forever...",
            "title_japanese": "\u4e09\u4ee3\u76ee\u3088, \u6c38\u4e45\u306b......!!",
            "title_romanji": "Sandaime yo, Towa ni......!!\u00a0",
            "aired": "2004-04-21T00:00:00+00:00",
            "score": 4.6,
            "filler": false,
            "recap": false,
            "forum_url": "https:\/\/myanimelist.net\/forum\/?topicid=104423"
        },
        {
            "mal_id": 81,
            "url": "https:\/\/myanimelist.net\/anime\/20\/Naruto\/episode\/81",
            "title": "Return of the Morning Mist",
            "title_japanese": "\u671d\u9727\u306e\u5e30\u90f7",
            "title_romanji": "Asagiri no Kikyou\u00a0",
            "aired": "2004-04-28T00:00:00+00:00",
            "score": 4.5,
            "filler": false,
            "recap": false,
            "forum_url": "https:\/\/myanimelist.net\/forum\/?topicid=104471"
        },
        {
            "mal_id": 82,
            "url": "https:\/\/myanimelist.net\/anime\/20\/Naruto\/episode\/82",
            "title": "Eye to Eye: Sharingan vs. Sharingan!",
            "title_japanese": "\u5199\u8f2a\u773cVS\u5199\u8f2a\u773c!!",
            "title_romanji": "Sharingan tai Sharingan!!\u00a0",
            "aired": "2004-05-05T00:00:00+00:00",
            "score": 4.5,
            "filler": false,
            "recap": false,
            "forum_url": "https:\/\/myanimelist.net\/forum\/?topicid=104482"
        },
        {
            "mal_id": 83,
            "url": "https:\/\/myanimelist.net\/anime\/20\/Naruto\/episode\/83",
            "title": "Jiraiya: Naruto's Potential Disaster!",
            "title_japanese": "\u304a\u304a, \u306e\u30a9\u301c\u3063!\u81ea\u6765\u4e5f\u306e\u5973\u96e3, \u30ca\u30eb\u30c8\u306e\u707d\u96e3",
            "title_romanji": "Ou, nou~! Jiraiya no Jonan, Naruto no Sainan\u00a0",
            "aired": "2004-05-12T00:00:00+00:00",
            "score": 4.5,
            "filler": false,
            "recap": false,
            "forum_url": "https:\/\/myanimelist.net\/forum\/?topicid=104492"
        },
        {
            "mal_id": 84,
            "url": "https:\/\/myanimelist.net\/anime\/20\/Naruto\/episode\/84",
            "title": "Roar, Chidori! Brother vs. Brother!",
            "title_japanese": "\u5538\u308c\u5343\u9ce5 \u5420\u3048\u308d\u30b5\u30b9\u30b1!",
            "title_romanji": "Unare Chidori, Hoero Sasuke!\u00a0",
            "aired": "2004-05-19T00:00:00+00:00",
            "score": 4.6,
            "filler": false,
            "recap": false,
            "forum_url": "https:\/\/myanimelist.net\/forum\/?topicid=104499"
        },
        {
            "mal_id": 85,
            "url": "https:\/\/myanimelist.net\/anime\/20\/Naruto\/episode\/85",
            "title": "Hate Among the Uchihas: The Last of the Clan!",
            "title_japanese": "\u611a\u304b\u306a\u308b\u5f1f\u3088 \u6068\u3081, \u618e\u3081!",
            "title_romanji": "Orokanaru Otouto yo Urame, Nikume!\u00a0",
            "aired": "2004-05-26T00:00:00+00:00",
            "score": 4.6,
            "filler": false,
            "recap": false,
            "forum_url": "https:\/\/myanimelist.net\/forum\/?topicid=104504"
        },
        {
            "mal_id": 86,
            "url": "https:\/\/myanimelist.net\/anime\/20\/Naruto\/episode\/86",
            "title": "A New Training Begins: I Will Be Strong!",
            "title_japanese": "\u4fee\u884c\u958b\u59cb \u30aa\u30ec\u306f\u305c\u3063\u3066\u30fc\u5f37\u304f\u306a\u308b!",
            "title_romanji": "Shugyou Kaishi, Ore wa Zettee Tsuyoku Naru!\u00a0",
            "aired": "2004-06-02T00:00:00+00:00",
            "score": 4.2,
            "filler": false,
            "recap": false,
            "forum_url": "https:\/\/myanimelist.net\/forum\/?topicid=104514"
        },
        {
            "mal_id": 87,
            "url": "https:\/\/myanimelist.net\/anime\/20\/Naruto\/episode\/87",
            "title": "Keep on Training: Pop Goes the Water Balloon!",
            "title_japanese": "\u6839\u6027!!!\u5272\u308c\u308d\u6c34\u98a8\u8239",
            "title_romanji": "Konjou!!! Warero Mizufuusen\u00a0",
            "aired": "2004-06-09T00:00:00+00:00",
            "score": 4.3,
            "filler": false,
            "recap": false,
            "forum_url": "https:\/\/myanimelist.net\/forum\/?topicid=104560"
        },
        {
            "mal_id": 88,
            "url": "https:\/\/myanimelist.net\/anime\/20\/Naruto\/episode\/88",
            "title": "Focal Point: The Mark of the Leaf",
            "title_japanese": "\u6728\u30ce\u8449\u30de\u30fc\u30af\u3068\u984d\u5f53\u3066",
            "title_romanji": "Konoha Maaku to Hitaiate\u00a0",
            "aired": "2004-06-16T00:00:00+00:00",
            "score": 4.4,
            "filler": false,
            "recap": false,
            "forum_url": "https:\/\/myanimelist.net\/forum\/?topicid=104574"
        },
        {
            "mal_id": 89,
            "url": "https:\/\/myanimelist.net\/anime\/20\/Naruto\/episode\/89",
            "title": "An Impossible Choice: The Pain Within Tsunade's Heart",
            "title_japanese": "\u6ce2\u7d0b",
            "title_romanji": "Hamon\u00a0",
            "aired": "2004-06-23T00:00:00+00:00",
            "score": 4.2,
            "filler": false,
            "recap": false,
            "forum_url": "https:\/\/myanimelist.net\/forum\/?topicid=104688"
        },
        {
            "mal_id": 90,
            "url": "https:\/\/myanimelist.net\/anime\/20\/Naruto\/episode\/90",
            "title": "Unforgivable! A Total Lack of Respect!",
            "title_japanese": "\u6012\u308a\u30d0\u30af\u30cf\u30c4!\u8a31\u3055\u306d\u30fc\u3063\u3066\u3070\u3088",
            "title_romanji": "Ikari Bakuhatsu! Yurusaneettebayo\u00a0",
            "aired": "2004-07-07T00:00:00+00:00",
            "score": 4.5,
            "filler": false,
            "recap": false,
            "forum_url": "https:\/\/myanimelist.net\/forum\/?topicid=104696"
        },
        {
            "mal_id": 91,
            "url": "https:\/\/myanimelist.net\/anime\/20\/Naruto\/episode\/91",
            "title": "Inheritence! The Necklace of Death!",
            "title_japanese": "\u521d\u4ee3\u706b\u5f71\u306e\u907a\u7523 \u6b7b\u3092\u547c\u3076\u9996\u98fe\u308a",
            "title_romanji": "Shodai Hokage no Isan Shi wo Yobu Kubikazari\u00a0",
            "aired": "2004-07-14T00:00:00+00:00",
            "score": 4.3,
            "filler": false,
            "recap": false,
            "forum_url": "https:\/\/myanimelist.net\/forum\/?topicid=104697"
        },
        {
            "mal_id": 92,
            "url": "https:\/\/myanimelist.net\/anime\/20\/Naruto\/episode\/92",
            "title": "A Dubious Offer! Tsunade's Choice!",
            "title_japanese": "YES\u304bNO\u304b!\u30c4\u30ca\u30c7\u306e\u56de\u7b54",
            "title_romanji": "YES ka NO ka! Tsunade no Kaitou\u00a0",
            "aired": "2004-07-21T00:00:00+00:00",
            "score": 4.3,
            "filler": false,
            "recap": false,
            "forum_url": "https:\/\/myanimelist.net\/forum\/?topicid=104709"
        },
        {
            "mal_id": 93,
            "url": "https:\/\/myanimelist.net\/anime\/20\/Naruto\/episode\/93",
            "title": "Breakdown! The Deal is Off!",
            "title_japanese": "\u4ea4\u6e09\u6c7a\u88c2!!",
            "title_romanji": "Koushou Ketsuretsu!\u00a0",
            "aired": "2004-07-28T00:00:00+00:00",
            "score": 4.4,
            "filler": false,
            "recap": false,
            "forum_url": "https:\/\/myanimelist.net\/forum\/?topicid=104784"
        },
        {
            "mal_id": 94,
            "url": "https:\/\/myanimelist.net\/anime\/20\/Naruto\/episode\/94",
            "title": "Attack! Fury of the Rasengan!",
            "title_japanese": "\u304f\u3089\u3048!\u6012\u308a\u306e\u87ba\u65cb\u4e38",
            "title_romanji": "Kurae! Ikari no Rasengan\u00a0",
            "aired": "2004-08-04T00:00:00+00:00",
            "score": 4.6,
            "filler": false,
            "recap": false,
            "forum_url": "https:\/\/myanimelist.net\/forum\/?topicid=104794"
        },
        {
            "mal_id": 95,
            "url": "https:\/\/myanimelist.net\/anime\/20\/Naruto\/episode\/95",
            "title": "The Fifth Hokage! A Life on the Line!",
            "title_japanese": "\u4e94\u4ee3\u76ee\u706b\u5f71 \u547d\u3092\u8ced\u3051\u305f\u6226\u3044",
            "title_romanji": "Godaime Hokage, Inochi wo Kaketa Tatakai!\u00a0",
            "aired": "2004-08-11T00:00:00+00:00",
            "score": 4.5,
            "filler": false,
            "recap": false,
            "forum_url": "https:\/\/myanimelist.net\/forum\/?topicid=104803"
        },
        {
            "mal_id": 96,
            "url": "https:\/\/myanimelist.net\/anime\/20\/Naruto\/episode\/96",
            "title": "Deadlock! Sannin Showdown!",
            "title_japanese": "\u4e09\u3059\u304f\u307f\u306e\u6226\u3044",
            "title_romanji": "Sansukumi no Tatakai\u00a0",
            "aired": "2004-08-11T00:00:00+00:00",
            "score": 4.6,
            "filler": false,
            "recap": false,
            "forum_url": "https:\/\/myanimelist.net\/forum\/?topicid=104814"
        },
        {
            "mal_id": 97,
            "url": "https:\/\/myanimelist.net\/anime\/20\/Naruto\/episode\/97",
            "title": "Kidnapped! Naruto's Hot Spring Adventure!",
            "title_japanese": "\u30ca\u30eb\u30c8\u306e\u6e6f\u3051\u3080\u308a\u73cd\u9053\u4e2d",
            "title_romanji": "Naruto no Yukemuri Chindouchuu\u00a0",
            "aired": "2004-08-18T00:00:00+00:00",
            "score": 3.7,
            "filler": true,
            "recap": false,
            "forum_url": "https:\/\/myanimelist.net\/forum\/?topicid=104820"
        },
        {
            "mal_id": 98,
            "url": "https:\/\/myanimelist.net\/anime\/20\/Naruto\/episode\/98",
            "title": "Tsunade's Warning: Ninja No More!",
            "title_japanese": "\u5fcd\u8005\u3092\u8f9e\u3081\u308d!\u30c4\u30ca\u30c7\u306e\u901a\u544a",
            "title_romanji": "Ninja wo Yamero! Tsunade no Tsuukoku\u00a0",
            "aired": "2004-08-25T00:00:00+00:00",
            "score": 4.2,
            "filler": false,
            "recap": false,
            "forum_url": "https:\/\/myanimelist.net\/forum\/?topicid=104939"
        },
        {
            "mal_id": 99,
            "url": "https:\/\/myanimelist.net\/anime\/20\/Naruto\/episode\/99",
            "title": "The Will of Fire Still Burns!",
            "title_japanese": "\u706b\u306e\u610f\u5fd7\u3092\u7d99\u3050\u3082\u306e",
            "title_romanji": "Hi no Ishi wo Tsugu Mono\u00a0",
            "aired": "2004-09-01T00:00:00+00:00",
            "score": 4.1,
            "filler": true,
            "recap": false,
            "forum_url": "https:\/\/myanimelist.net\/forum\/?topicid=104942"
        },
        {
            "mal_id": 100,
            "url": "https:\/\/myanimelist.net\/anime\/20\/Naruto\/episode\/100",
            "title": "Sensei and Student: The Bond of the Shinobi",
            "title_japanese": "\u71b1\u8840\u5e2b\u5f1f\u306e\u7d46\u301c\u7537\u304c\u5fcd\u9053\u3092\u8cab\u304f\u3068\u304d\u301c",
            "title_romanji": "Nekketsu Shitei no Kizuna: Otoko ga Nindou wo Tsuranuku toki\u00a0",
            "aired": "2004-09-08T00:00:00+00:00",
            "score": 4.3,
            "filler": false,
            "recap": false,
            "forum_url": "https:\/\/myanimelist.net\/forum\/?topicid=104946"
        }
    ]
}